eosce/__init__.py
eosce/cli.py
eosce/efp.onnx
eosce/mappings.joblib
eosce/models.py
eosce/utils.py
eosce-0.2.0.dist-info/LICENSE
eosce-0.2.0.dist-info/METADATA
eosce-0.2.0.dist-info/WHEEL
eosce-0.2.0.dist-info/entry_points.txt
eosce-0.2.0.dist-info/RECORD
