Metadata-Version: 2.1
Name: eosce
Version: 0.2.0
Summary: Ersilia Compound Embeddings
Author: Ersilia
Author-email: hello@ersilia.io
Requires-Python: >=3.10,<4.0
Classifier: Programming Language :: Python :: 3
Classifier: Programming Language :: Python :: 3.10
Classifier: Programming Language :: Python :: 3.11
Provides-Extra: gpu
Requires-Dist: click (==8.1.7)
Requires-Dist: joblib (==1.2.0)
Requires-Dist: onnxruntime (>=1.14.0,<2.0.0)
Requires-Dist: onnxruntime-gpu (==1.14.0) ; extra == "gpu"
Requires-Dist: rdkit (==2023.9.5)
